gdpy3/__about__.py
gdpy3/__init__.py
gdpy3/__main__.py
gdpy3/_json.py
gdpy3/_zipfile.py
gdpy3/cli.py
gdpy3/deprecation.py
gdpy3/glogger.py
gdpy3/server.py
gdpy3/tools.py
gdpy3/utils.py
gdpy3/GTCv3/__init__.py
gdpy3/GTCv3/data1d.py
gdpy3/GTCv3/equilibrium.py
gdpy3/GTCv3/flux3d.py
gdpy3/GTCv3/gtc.py
gdpy3/GTCv3/history.py
gdpy3/GTCv3/meshgrid.py
gdpy3/GTCv3/misc.py
gdpy3/GTCv3/phase2d.py
gdpy3/GTCv3/rzf.py
gdpy3/GTCv3/simugrid.py
gdpy3/GTCv3/snapevphase.py
gdpy3/GTCv3/snapphi.py
gdpy3/GTCv3/snapshot.py
gdpy3/GTCv3/theta1d.py
gdpy3/GTCv3/trackparticle.py
gdpy3/GTCv3/zetapsi3d.py
gdpy3/GUI/__init__.py
gdpy3/GUI/ipynb.py
gdpy3/GUI/tk.py
gdpy3/GUI/tkSliderTest.py
gdpy3/GUI/tkSliderWidget.py
gdpy3/analysis/__init__.py
gdpy3/analysis/series.py
gdpy3/cores/__init__.py
gdpy3/cores/base.py
gdpy3/cores/converter.py
gdpy3/cores/digger.py
gdpy3/cores/exporter.py
gdpy3/gdpy3-data/git-version
gdpy3/gdpy3-data/icon/gdpy3_128.gif
gdpy3/gdpy3-data/icon/gdpy3_128.icns
gdpy3/gdpy3-data/icon/gdpy3_128.ico
gdpy3/gdpy3-data/icon/gdpy3_128.png
gdpy3/gdpy3-data/ipynb_scrollbar/locale
gdpy3/gdpy3-data/ipynb_scrollbar/scroll_bar.css
gdpy3/gdpy3-data/ipynb_scrollbar/scroll_bar.html
gdpy3/gdpy3-data/ipynb_scrollbar/scroll_bar.js
gdpy3/gdpy3-data/mpl-stylelib/gdpy3-latex.mplstyle
gdpy3/gdpy3-data/mpl-stylelib/gdpy3-notebook.mplstyle
gdpy3/gdpy3-data/mpl-stylelib/gdpy3-ocean.mplstyle
gdpy3/gdpy3-data/mpl-stylelib/gdpy3-paper-aip.mplstyle
gdpy3/gdpy3-data/mpl-stylelib/readme.txt
gdpy3/loaders/__init__.py
gdpy3/loaders/base.py
gdpy3/loaders/cachepck.py
gdpy3/loaders/dirraw.py
gdpy3/loaders/hdf5pck.py
gdpy3/loaders/jsonpck.py
gdpy3/loaders/npzpck.py
gdpy3/loaders/sftpraw.py
gdpy3/loaders/tarraw.py
gdpy3/loaders/zipraw.py
gdpy3/processors/__init__.py
gdpy3/processors/_mp_rwlock.py
gdpy3/processors/lib.py
gdpy3/processors/misc.py
gdpy3/processors/multiprocessor.py
gdpy3/processors/processor.py
gdpy3/savers/__init__.py
gdpy3/savers/base.py
gdpy3/savers/cachepck.py
gdpy3/savers/hdf5pck.py
gdpy3-0.8.5.dist-info/licenses/LICENSE
gdpy3-0.8.5.dist-info/METADATA
gdpy3-0.8.5.dist-info/WHEEL
gdpy3-0.8.5.dist-info/entry_points.txt
gdpy3-0.8.5.dist-info/top_level.txt
gdpy3-0.8.5.dist-info/RECORD
