Metadata-Version: 2.4
Name: gdpy3
Version: 0.8.5
Summary: Gyrokinetic Toroidal Code Data Processing tools written in python3
Home-page: https://github.com/shmilee/gdpy3.git
Author: shmilee
Author-email: shmilee.zju@gmail.com
License: MIT
Keywords: GTC,matplotlib
Platform: Linux
Platform: MacOS X
Platform: Windows
Classifier: Development Status :: 4 - Beta
Classifier: Environment :: Console
Classifier: Environment :: Plugins
Classifier: Environment :: X11 Applications
Classifier: Intended Audience :: Science/Research
Classifier: Operating System :: MacOS :: MacOS X
Classifier: Operating System :: Microsoft :: Windows
Classifier: Operating System :: OS Independent
Classifier: Operating System :: POSIX :: Linux
Classifier: Programming Language :: Python :: 3 :: Only
Classifier: Programming Language :: Python :: 3.9
Classifier: Programming Language :: Python :: 3.10
Classifier: Programming Language :: Python :: 3.11
Classifier: Programming Language :: Python :: 3.12
Classifier: Programming Language :: Python :: 3.13
Classifier: Topic :: Scientific/Engineering :: Physics
Classifier: Topic :: Scientific/Engineering :: Visualization
License-File: LICENSE
Requires-Dist: numpy>=1.10.0
Requires-Dist: scipy>=0.14.0
Requires-Dist: matplotlib>=2.0.0
Provides-Extra: data
Requires-Dist: h5py>=2.6.0; extra == "data"
Requires-Dist: paramiko>=2.0.0; extra == "data"
Provides-Extra: tkui
Requires-Dist: screeninfo>=0.4.1; extra == "tkui"
Provides-Extra: nbui
Requires-Dist: ipython[notebook]; extra == "nbui"
Requires-Dist: ipywidgets; extra == "nbui"
Provides-Extra: imcat
Requires-Dist: pillow>=4.0.0; extra == "imcat"
Requires-Dist: libsixel-python>=0.5.0; extra == "imcat"
Provides-Extra: autocomplete
Requires-Dist: argcomplete>=2.0.0; extra == "autocomplete"
Dynamic: author
Dynamic: author-email
Dynamic: classifier
Dynamic: description
Dynamic: description-content-type
Dynamic: home-page
Dynamic: keywords
Dynamic: license
Dynamic: license-file
Dynamic: platform
Dynamic: provides-extra
Dynamic: requires-dist
Dynamic: summary
